odoo/addons/l10n_it_fatturapa_out_ddt/README.rst
odoo/addons/l10n_it_fatturapa_out_ddt/__init__.py
odoo/addons/l10n_it_fatturapa_out_ddt/__manifest__.py
odoo/addons/l10n_it_fatturapa_out_ddt/i18n/it.po
odoo/addons/l10n_it_fatturapa_out_ddt/i18n/l10n_it_fatturapa_out_ddt.pot
odoo/addons/l10n_it_fatturapa_out_ddt/readme/CONTRIBUTORS.rst
odoo/addons/l10n_it_fatturapa_out_ddt/readme/DESCRIPTION.rst
odoo/addons/l10n_it_fatturapa_out_ddt/readme/USAGE.rst
odoo/addons/l10n_it_fatturapa_out_ddt/static/description/icon.png
odoo/addons/l10n_it_fatturapa_out_ddt/static/description/index.html
odoo/addons/l10n_it_fatturapa_out_ddt/tests/__init__.py
odoo/addons/l10n_it_fatturapa_out_ddt/tests/test_fatturapa_ddt.py
odoo/addons/l10n_it_fatturapa_out_ddt/tests/data/IT06363391001_00006.xml
odoo/addons/l10n_it_fatturapa_out_ddt/tests/data/IT06363391001_00007.xml
odoo/addons/l10n_it_fatturapa_out_ddt/wizard/__init__.py
odoo/addons/l10n_it_fatturapa_out_ddt/wizard/wizard_export_fatturapa.py
odoo/addons/l10n_it_fatturapa_out_ddt/wizard/wizard_export_fatturapa_view.xml
odoo11_addon_l10n_it_fatturapa_out_ddt-11.0.1.1.0.dist-info/METADATA
odoo11_addon_l10n_it_fatturapa_out_ddt-11.0.1.1.0.dist-info/WHEEL
odoo11_addon_l10n_it_fatturapa_out_ddt-11.0.1.1.0.dist-info/top_level.txt
odoo11_addon_l10n_it_fatturapa_out_ddt-11.0.1.1.0.dist-info/RECORD
