Metadata-Version: 2.1
Name: odoo11-addon-l10n-it-fatturapa-out-ddt
Version: 11.0.1.1.0
Summary: Modulo ponte tra emissione fatture elettroniche e DDT
Home-page: https://github.com/OCA/l10n-italy/tree/11.0/l10n_it_fatturapa_out_ddt
Author: Agile Business Group, Odoo Community Association (OCA)
Author-email: support@odoo-community.org
License: LGPL-3
Platform: UNKNOWN
Classifier: Programming Language :: Python
Classifier: Framework :: Odoo
Classifier: License :: OSI Approved :: GNU Lesser General Public License v3 (LGPLv3)
Classifier: Development Status :: 4 - Beta
Requires-Python: >=2.7, !=3.0.*, !=3.1.*, !=3.2.*, !=3.3.*, !=3.4.*
Requires-Dist: odoo11-addon-l10n-it-ddt
Requires-Dist: odoo11-addon-l10n-it-fatturapa-out
Requires-Dist: odoo (<11.1dev,>=11.0a)
